private_assistant_comms_satellite/__init__.py
private_assistant_comms_satellite/audio_processing.py
private_assistant_comms_satellite/cli.py
private_assistant_comms_satellite/main.py
private_assistant_comms_satellite/py.typed
private_assistant_comms_satellite/satellite.py
private_assistant_comms_satellite/silero_vad.py
private_assistant_comms_satellite/utils/__init__.py
private_assistant_comms_satellite/utils/config.py
private_assistant_comms_satellite/utils/debug_audio.py
private_assistant_comms_satellite/utils/ground_station_client.py
private_assistant_comms_satellite/utils/sound_generation.py
private_assistant_comms_satellite-1.6.0.dist-info/licenses/LICENSE
private_assistant_comms_satellite-1.6.0.dist-info/WHEEL
private_assistant_comms_satellite-1.6.0.dist-info/entry_points.txt
private_assistant_comms_satellite-1.6.0.dist-info/METADATA
private_assistant_comms_satellite-1.6.0.dist-info/RECORD
