Metadata-Version: 2.4
Name: private-assistant-comms-satellite
Version: 1.6.0
Summary: The satellite is an open source library to work with the private assistant oecosystem built to run on edge devices. It allows the other components to interact speech based with the user and listen for user keywords to activate.
Keywords: 
Author: stkr22
Author-email: stkr22 <stkr22@github.com>
License-Expression: GPL-3.0-only
License-File: LICENSE
Classifier: Development Status :: 3 - Alpha
Classifier: Environment :: Console
Classifier: Programming Language :: Python
Classifier: Intended Audience :: Developers
Classifier: Operating System :: OS Independent
Requires-Dist: pyyaml
Requires-Dist: pydantic
Requires-Dist: private-assistant-commons~=5.4.0
Requires-Dist: speexdsp-ns~=0.1.2
Requires-Dist: numpy~=2.3.0
Requires-Dist: websockets~=16.0
Requires-Dist: onnxruntime~=1.23.2
Requires-Dist: pysilero-vad~=3.2.0
Requires-Dist: typer~=0.21.0
Requires-Dist: private-assistant-openwakeword~=0.6.0
Requires-Dist: sounddevice~=0.5.1
Requires-Python: >=3.12, <3.13
Project-URL: Homepage, https://github.com/stkr22/private-assistant-comms-satellite-py
Project-URL: Repository, https://github.com/stkr22/private-assistant-comms-satellite-py
Project-URL: Documentation, https://github.com/stkr22/private-assistant-comms-satellite-py/tree/main/docs
Project-URL: Issues, https://github.com/stkr22/private-assistant-comms-satellite-py/issues
Project-URL: Changelog, https://github.com/stkr22/private-assistant-comms-satellite-py/blob/main/CHANGELOG.md
